{
  "success": true,
  "directory": "/home/jason/Videos/screenRecordings/screen_recording_2025_03_18_at_8_13_45_am",
  "timestamp": "2025-04-14 07:35:11",
  "message": "Generated URLs for 103 images",
  "count": 103,
  "image_urls": [
    "http://localhost:7779/images/frame_000001.jpg",
    "http://localhost:7779/images/frame_000002.jpg",
    "http://localhost:7779/images/frame_000003.jpg",
    "http://localhost:7779/images/frame_000004.jpg",
    "http://localhost:7779/images/frame_000005.jpg",
    "http://localhost:7779/images/frame_000006.jpg",
    "http://localhost:7779/images/frame_000007.jpg",
    "http://localhost:7779/images/frame_000008.jpg",
    "http://localhost:7779/images/frame_000009.jpg",
    "http://localhost:7779/images/frame_000010.jpg",
    "http://localhost:7779/images/frame_000011.jpg",
    "http://localhost:7779/images/frame_000012.jpg",
    "http://localhost:7779/images/frame_000013.jpg",
    "http://localhost:7779/images/frame_000014.jpg",
    "http://localhost:7779/images/frame_000015.jpg",
    "http://localhost:7779/images/frame_000016.jpg",
    "http://localhost:7779/images/frame_000017.jpg",
    "http://localhost:7779/images/frame_000018.jpg",
    "http://localhost:7779/images/frame_000019.jpg",
    "http://localhost:7779/images/frame_000020.jpg",
    "http://localhost:7779/images/frame_000021.jpg",
    "http://localhost:7779/images/frame_000022.jpg",
    "http://localhost:7779/images/frame_000023.jpg",
    "http://localhost:7779/images/frame_000024.jpg",
    "http://localhost:7779/images/frame_000025.jpg",
    "http://localhost:7779/images/frame_000026.jpg",
    "http://localhost:7779/images/frame_000027.jpg",
    "http://localhost:7779/images/frame_000028.jpg",
    "http://localhost:7779/images/frame_000029.jpg",
    "http://localhost:7779/images/frame_000030.jpg",
    "http://localhost:7779/images/frame_000031.jpg",
    "http://localhost:7779/images/frame_000032.jpg",
    "http://localhost:7779/images/frame_000033.jpg",
    "http://localhost:7779/images/frame_000034.jpg",
    "http://localhost:7779/images/frame_000035.jpg",
    "http://localhost:7779/images/frame_000036.jpg",
    "http://localhost:7779/images/frame_000037.jpg",
    "http://localhost:7779/images/frame_000038.jpg",
    "http://localhost:7779/images/frame_000039.jpg",
    "http://localhost:7779/images/frame_000040.jpg",
    "http://localhost:7779/images/frame_000041.jpg",
    "http://localhost:7779/images/frame_000042.jpg",
    "http://localhost:7779/images/frame_000043.jpg",
    "http://localhost:7779/images/frame_000044.jpg",
    "http://localhost:7779/images/frame_000045.jpg",
    "http://localhost:7779/images/frame_000046.jpg",
    "http://localhost:7779/images/frame_000047.jpg",
    "http://localhost:7779/images/frame_000048.jpg",
    "http://localhost:7779/images/frame_000049.jpg",
    "http://localhost:7779/images/frame_000050.jpg",
    "http://localhost:7779/images/frame_000051.jpg",
    "http://localhost:7779/images/frame_000052.jpg",
    "http://localhost:7779/images/frame_000053.jpg",
    "http://localhost:7779/images/frame_000054.jpg",
    "http://localhost:7779/images/frame_000055.jpg",
    "http://localhost:7779/images/frame_000056.jpg",
    "http://localhost:7779/images/frame_000057.jpg",
    "http://localhost:7779/images/frame_000058.jpg",
    "http://localhost:7779/images/frame_000059.jpg",
    "http://localhost:7779/images/frame_000060.jpg",
    "http://localhost:7779/images/frame_000061.jpg",
    "http://localhost:7779/images/frame_000062.jpg",
    "http://localhost:7779/images/frame_000063.jpg",
    "http://localhost:7779/images/frame_000064.jpg",
    "http://localhost:7779/images/frame_000065.jpg",
    "http://localhost:7779/images/frame_000066.jpg",
    "http://localhost:7779/images/frame_000067.jpg",
    "http://localhost:7779/images/frame_000068.jpg",
    "http://localhost:7779/images/frame_000069.jpg",
    "http://localhost:7779/images/frame_000070.jpg",
    "http://localhost:7779/images/frame_000071.jpg",
    "http://localhost:7779/images/frame_000072.jpg",
    "http://localhost:7779/images/frame_000073.jpg",
    "http://localhost:7779/images/frame_000074.jpg",
    "http://localhost:7779/images/frame_000075.jpg",
    "http://localhost:7779/images/frame_000076.jpg",
    "http://localhost:7779/images/frame_000077.jpg",
    "http://localhost:7779/images/frame_000078.jpg",
    "http://localhost:7779/images/frame_000079.jpg",
    "http://localhost:7779/images/frame_000080.jpg",
    "http://localhost:7779/images/frame_000081.jpg",
    "http://localhost:7779/images/frame_000082.jpg",
    "http://localhost:7779/images/frame_000083.jpg",
    "http://localhost:7779/images/frame_000084.jpg",
    "http://localhost:7779/images/frame_000085.jpg",
    "http://localhost:7779/images/frame_000086.jpg",
    "http://localhost:7779/images/frame_000087.jpg",
    "http://localhost:7779/images/frame_000088.jpg",
    "http://localhost:7779/images/frame_000089.jpg",
    "http://localhost:7779/images/frame_000090.jpg",
    "http://localhost:7779/images/frame_000091.jpg",
    "http://localhost:7779/images/frame_000092.jpg",
    "http://localhost:7779/images/frame_000093.jpg",
    "http://localhost:7779/images/frame_000094.jpg",
    "http://localhost:7779/images/frame_000095.jpg",
    "http://localhost:7779/images/frame_000096.jpg",
    "http://localhost:7779/images/frame_000097.jpg",
    "http://localhost:7779/images/frame_000098.jpg",
    "http://localhost:7779/images/frame_000099.jpg",
    "http://localhost:7779/images/frame_000100.jpg",
    "http://localhost:7779/images/frame_000101.jpg",
    "http://localhost:7779/images/frame_000102.jpg",
    "http://localhost:7779/images/frame_000103.jpg"
  ],
  "timeout_minutes": 60,
  "auto_unload_at": "2025-04-14 08:35:11",
  "time_remaining": "59m 59s"
}